restream_io/__init__.py
restream_io/cli.py
restream_io-0.6.0.dist-info/METADATA
restream_io-0.6.0.dist-info/WHEEL
restream_io-0.6.0.dist-info/entry_points.txt
restream_io-0.6.0.dist-info/top_level.txt
restream_io-0.6.0.dist-info/RECORD
