Metadata-Version: 2.4
Name: restream.io
Version: 0.6.0
Summary: CLI for interacting with the Restream.io API
License: BSD-3-Clause
Requires-Python: >=3.11
Requires-Dist: click>=8.2.1
Requires-Dist: pyrestream>=0.1.0
